tntn/__init__.py
tntn/__main__.py
tntn/__version__.py
tntn/tntn.py
tntn/urls.toml
tntn/util.py
tntn-23.5.0.dist-info/entry_points.txt
tntn-23.5.0.dist-info/WHEEL
tntn-23.5.0.dist-info/METADATA
tntn-23.5.0.dist-info/licenses/LICENSE.md
tntn-23.5.0.dist-info/RECORD
