Metadata-Version: 2.1
Name: tntn
Version: 23.5.0
Summary: Python wrapper library for tunneling apps
License: MIT
Author-email: dowon <ks2515@naver.com>
Requires-Python: >=3.7
Requires-Dist: tomli; python_version < "3.11"
Requires-Dist: tqdm
Project-URL: repository, https://github.com/Bing-su/tntn
